{"date": "2025-07-24T15:30:00", "completed": true}
{"date": "2025-07-25T18:03:22.331039", "subject": "Biology Quiz", "completed": true}
{"date": "2025-07-25T18:03:22.331544", "subject": "History Notes", "completed": true}
{"date": "2025-07-25T18:03:22.332550", "subject": "Math Practice", "completed": true}
{"date": "2025-07-25T18:15:24.904991", "subject": "Biology Quiz", "completed": true}
{"date": "2025-07-25T18:15:24.905990", "subject": "History Notes", "completed": true}
{"date": "2025-07-25T18:15:24.905990", "subject": "Math Practice", "completed": false}
{"date": "2025-07-25T18:17:24.586150", "subject": "Biology Quiz", "completed": true}
{"date": "2025-07-25T18:17:24.586150", "subject": "History Notes", "completed": true}
{"date": "2025-07-25T18:17:24.587150", "subject": "Math Practice", "completed": true}
{"date": "2025-07-26T18:19:32.946389", "subject": "Biology Quiz", "completed": false}
{"date": "2025-07-26T18:19:32.947276", "subject": "History Notes", "completed": true}
{"date": "2025-07-26T18:19:32.947276", "subject": "Math Practice", "completed": true}
